AUTHORS
CHANGELOG.txt
DESCRIPTION
LICENSE
MANIFEST.in
README.rst
setup.cfg
setup.py
pyplaintext/__init__.py
pyplaintext/converter.py
pyplaintext.egg-info/PKG-INFO
pyplaintext.egg-info/SOURCES.txt
pyplaintext.egg-info/dependency_links.txt
pyplaintext.egg-info/requires.txt
pyplaintext.egg-info/top_level.txt
pyplaintext/tests/.coveragerc
pyplaintext/tests/__init__.py
pyplaintext/tests/converter_tests.py