Metadata-Version: 1.0
Name: pyplaintext
Version: 0.1
Summary: A HTML to plaintext converter.
